{
  "id": "assistant-hub-builtin-prd-split",
  "name": "assistant-hub-builtin-prd-split",
  "title": "Assistant Hub: built-in PRD-split assistant + user-created assistants",
  "description": "",
  "status": "completed",
  "dev_type": null,
  "scope": null,
  "package": null,
  "priority": "P2",
  "creator": "xuning",
  "assignee": "xuning",
  "createdAt": "2026-05-18",
  "completedAt": "2026-05-21",
  "branch": null,
  "base_branch": "main",
  "worktree_path": null,
  "commit": null,
  "pr_url": null,
  "subtasks": [],
  "children": [],
  "parent": null,
  "relatedFiles": [],
  "notes": "",
  "meta": {}
}